{"stats":{"minecraft:mined":{"stoneworks:stone_plates":1,"minerally:deepslate_gold_pile_0":2,"minerally:deepslate_emerald_crystal_0":1,"minerally:deepslate_gold_pile_1":2,"minerally:deepslate_emerald_crystal_1":1,"minerally:deepslate_diamond_crystal_0":1,"cobblemon:dawn_stone_ore":2,"minecraft:spruce_trapdoor":1,"minecraft:deepslate_tile_wall":7,"minecraft:grass_block":337,"minecraft:stone_brick_wall":5,"minerally:coal_pile_0":1,"minecraft:white_concrete":11,"minecraft:deepslate_tile_stairs":8,"minecraft:green_concrete":5,"minecraft:chiseled_stone_bricks":2,"minecraft:cobbled_deepslate":2,"minecraft:iron_ore":10,"regions_unexplored:mossy_stone":4,"stoneworks:stone_tiles":3,"minecraft:enchanting_table":1,"minerally:deepslate_coal_pile_0":5,"stoneworks:stone_tile_wall":7,"minecraft:iron_bars":2,"minerally:diamond_rock":1,"minerally:coal_pile_1":1,"minerally:deepslate_diamond_crystal_1":1,"minecraft:azalea":1,"minecraft:iron_block":1,"minecraft:player_head":1,"minerally:deepslate_redstone_pile_0":1,"minecraft:deepslate_redstone_ore":9,"minerally:deepslate_redstone_pile":1,"visualworkbench:minecraft/crafting_table":3,"minerally:deepslate_coal_pile_1":5,"minerally:deepslate_emerald_crystal":1,"minerally:deepslate_copper_pile":2,"minecraft:cobblestone":11,"minecraft:birch_wood":3,"minecraft:chain":1,"regions_unexplored:hyssop":1,"stoneworks:stone_pillar":2,"minerally:deepslate_geode":1,"regions_unexplored:sandy_tall_grass":1,"regions_unexplored:mauve_planks":4,"minecraft:oak_log":127,"minecraft:dirt":746,"minecraft:mangrove_log":6,"minecraft:deepslate":43,"minecraft:deepslate_tiles":455,"minecraft:tuff":1,"biomeswevegone:cyan_amaranth":1,"minecraft:mossy_cobblestone":1,"minecraft:deepslate_diamond_ore":23,"minecraft:dark_oak_log":7,"minecraft:glow_lichen":1,"minerally:deepslate_iron_pile_1":5,"minerally:deepslate_diamond_crystal":1,"minecraft:furnace":2,"minecraft:andesite":284,"minecraft:diamond_block":2,"minecraft:gold_block":2,"minerally:deepslate_iron_pile_0":5,"minerally:deepslate_iron_pile":5,"minecraft:bell":1,"minerally:deepslate_gold_pile":2,"minecraft:deepslate_iron_ore":12,"regions_unexplored:medium_grass":2,"minecraft:stone":1467,"minecraft:green_wool":2,"minerally:coal_pile":1,"minecraft:oak_slab":5,"minecraft:glass_pane":14,"minerally:deepslate_redstone_pile_1":2,"minecraft:oak_fence":22,"minecraft:short_grass":2,"minecraft:oak_wood":97,"minecraft:tall_grass":3,"minecraft:copper_ore":10,"regions_unexplored:mauve_log":2,"minecraft:deepslate_gold_ore":19,"stoneworks:andesite_tiles":1,"minecraft:sea_pickle":1,"minecraft:birch_leaves":5,"minerally:deepslate_coal_pile":5,"minecraft:coal_ore":62,"minecraft:gravel":20,"minecraft:stone_bricks":2},"minecraft:used":{"justhammers:netherite_destructor_hammer":28,"minecraft:light_blue_banner":27,"arts_and_crafts:gypsum_bricks":17,"minecraft:player_head":1,"minecraft:deepslate_tile_slab":4,"minecraft:deepslate_brick_slab":194,"stoneworks:quartz_shingle_slab":8,"minecraft:quartz_slab":2,"minecraft:lantern":4,"minecraft:polished_andesite_stairs":10,"minecraft:stone_brick_stairs":25,"minecraft:stone_bricks":32,"minecraft:red_carpet":1,"minecraft:redstone_lamp":92,"minecraft:furnace":1,"stoneworks:calcite_brick_stairs":228,"minecraft:egg":4,"handcrafted:stone_pillar_trim":1,"minecraft:torchflower":2,"minecraft:stone_pickaxe":43,"minecraft:birch_wood":3,"minecraft:wooden_pickaxe":20,"minecraft:black_glazed_terracotta":1,"minecraft:redstone_block":9,"regions_unexplored:mauve_planks":4,"minecraft:stone_brick_wall":20,"minecraft:deepslate_brick_stairs":227,"minecraft:redstone_torch":2,"minecraft:deepslate_tiles":61,"waystones:waystone":1,"minecraft:black_concrete":74,"minecraft:daylight_detector":15,"minecraft:gray_stained_glass_pane":373,"arts_and_crafts:light_gray_terracotta_shingles":37,"minecraft:white_glazed_terracotta":1,"minecraft:gravel":6,"additional_lights:fire_pit_l_stone_bricks":1,"minecraft:chain":65,"minecraft:white_concrete":352,"stoneworks:stone_tile_wall":12,"biomeswevegone:rocky_stone":1,"minecraft:oak_fence":22,"stoneworks:andesite_tiles":1,"stoneworks:stone_plates":1,"minecraft:red_concrete":260,"minecraft:dirt":38,"minecraft:hopper":1,"minecraft:light_gray_glazed_terracotta":1,"minecraft:oak_wood":21,"minecraft:glowstone":17,"minecraft:deepslate_tile_stairs":84,"regions_unexplored:flowering_leaves":4,"biomeswevegone:ebony_fence":9,"stoneworks:stone_pillar":2,"minecraft:cobbled_deepslate":29,"rechiseled:dark_oak_planks_tiles_connecting":83,"stoneworks:stone_tiles":25,"minecraft:deepslate_bricks":8,"minecraft:oak_slab":98,"minecraft:crafting_table":4,"minecraft:brown_glazed_terracotta":7,"minecraft:book":3,"minecraft:deepslate_tile_wall":7,"minecraft:oak_log":226,"minecraft:diamond_pickaxe":780,"minecraft:diamond_shovel":148,"minecraft:iron_pickaxe":251,"rechiseled:quartz_block_chiseled_pillar_connecting":331,"minecraft:stone_axe":256,"arts_and_crafts:terracotta_shingles":11,"minecraft:chiseled_stone_bricks":2,"minecraft:cobblestone":200,"minecraft:glass_pane":17,"minecraft:sea_pickle":3},"minecraft:picked_up":{"minecraft:flower_pot":1,"minecraft:enchanted_book":3,"minecraft:light":1,"minecraft:string":3,"minecraft:raw_copper":15,"minecraft:sea_pickle":3,"minecraft:deepslate_tiles":418,"minecraft:cobbled_deepslate":48,"minecraft:azalea":3,"minecraft:enchanted_golden_apple":1,"minecraft:deepslate_tile_wall":7,"minecraft:mangrove_log":6,"minecraft:furnace":2,"minecraft:spruce_pressure_plate":1,"minecraft:stick":3,"minecraft:oak_fence":22,"minecraft:porkchop":34,"minecraft:deepslate_tile_stairs":8,"regions_unexplored:daisy":6,"minecraft:rotten_flesh":1,"regions_unexplored:mauve_log":2,"minecraft:iron_block":2,"minecraft:green_wool":2,"cobblemon:verdant_ball":1,"minecraft:iron_bars":2,"stoneworks:stone_plates":2,"minecraft:cobblestone":1199,"minecraft:enchanting_table":1,"minecraft:barrier":1,"minecraft:feather":16,"minecraft:repeater":2,"minecraft:andesite":276,"minecraft:flint":3,"stoneworks:stone_tile_wall":7,"minecraft:tuff":1,"minecraft:lapis_lazuli":2,"minecraft:dirt":929,"minecraft:lantern":1,"minecraft:wheat_seeds":9,"minecraft:raw_gold":27,"minecraft:bell":1,"minecraft:birch_wood":3,"minecraft:oak_planks":7,"minecraft:debug_stick":1,"minecraft:diamond_block":2,"minecraft:dark_oak_log":7,"regions_unexplored:pink_lupine":1,"minecraft:mossy_cobblestone":4,"regions_unexplored:mauve_planks":4,"regions_unexplored:hyssop":12,"minecraft:green_concrete":2,"minecraft:diamond":31,"cobblemon:poke_ball":6,"minecraft:soul_lantern":1,"waystones:waystone":1,"minecraft:white_concrete":9,"minecraft:emerald":4,"minecraft:chorus_fruit":1,"minecraft:dark_oak_fence":1,"minecraft:diamond_pickaxe":1,"minecraft:mud":1,"minecraft:crafting_table":3,"minecraft:chicken":18,"minecraft:stone_brick_wall":5,"minecraft:gold_block":7,"stoneworks:andesite_tiles":1,"minecraft:cracked_stone_bricks":14,"minecraft:beef":31,"minecraft:player_head":1,"minecraft:spruce_trapdoor":1,"minecraft:egg":8,"minecraft:raw_iron":44,"minecraft:stone":40,"minecraft:oak_door":1,"minecraft:raw_gold_block":3,"minecraft:redstone":47,"cobblemon:dawn_stone":2,"minecraft:saddle":1,"minecraft:mutton":32,"minecraft:white_wool":18,"minecraft:tripwire_hook":3,"minecraft:leather":24,"minecraft:torchflower":1,"minecraft:oak_log":853,"minecraft:cobblestone_wall":1,"minecraft:light_blue_banner":1,"stoneworks:stone_tiles":5,"minecraft:stone_bricks":23,"numismatic-overhaul:bronze_coin":34,"minecraft:oak_slab":4,"minecraft:dark_oak_slab":6,"stoneworks:stone_pillar":2,"minecraft:chiseled_stone_bricks":2,"minecraft:dandelion":1,"minecraft:gravel":15,"minecraft:spider_eye":1,"minecraft:oak_wood":183,"minecraft:pumpkin_seeds":3,"regions_unexplored:fireweed":8,"minecraft:stone_axe":1,"minecraft:gray_wool":1,"minecraft:coal":88},"minecraft:killed_by":{"minecraft:player":1},"minecraft:crafted":{"minecraft:oak_planks":96,"minecraft:stone":524,"minecraft:diamond_shovel":1,"minecraft:chiseled_stone_bricks":2,"minecraft:stone_bricks":22,"minecraft:oak_fence":12,"stoneworks:stone_tiles":1,"stoneworks:stone_plates":1,"minecraft:oak_slab":102,"minecraft:crafting_table":2,"minecraft:wooden_pickaxe":1,"minecraft:copper_ingot":140,"stoneworks:stone_pillar":2,"minecraft:stone_brick_stairs":33,"minecraft:diamond_pickaxe":1,"sophisticatedbackpacks:diamond_backpack":1,"minecraft:stick":20,"minecraft:iron_ingot":37,"minecraft:iron_pickaxe":1,"minecraft:gold_ingot":17,"minecraft:deepslate_tile_slab":4,"minecraft:stone_brick_wall":15,"minecraft:furnace":1,"stoneworks:andesite_tiles":1,"regions_unexplored:mauve_planks":8,"minecraft:stone_pickaxe":1,"minecraft:deepslate_tile_wall":5,"sophisticatedbackpacks:iron_backpack":1,"stoneworks:stone_tile_wall":5,"sophisticatedbackpacks:gold_backpack":1,"minecraft:stone_axe":1,"minecraft:air":0,"minecraft:deepslate_tile_stairs":45},"minecraft:custom":{"lootr:looted_stat":109,"minecraft:interact_with_crafting_table":22,"minecraft:open_barrel":5,"minecraft:bell_ring":2,"minecraft:leave_game":8,"minecraft:time_since_death":371414,"minecraft:sprint_one_cm":340976,"minecraft:drop":86,"minecraft:talked_to_villager":18,"minecraft:play_time":706773,"minecraft:deaths":3,"minecraft:jump":2653,"minecraft:walk_on_water_one_cm":45533,"minecraft:interact_with_furnace":39,"minecraft:interact_with_cartography_table":1,"minecraft:interact_with_loom":2,"minecraft:waystone_activated":6,"minecraft:pokemon_caught":3,"minecraft:damage_dealt":68,"minecraft:crouch_one_cm":46800,"minecraft:horse_one_cm":15851,"minecraft:mob_kills":1,"minecraft:interact_with_anvil":3,"minecraft:inspect_hopper":1,"minecraft:climb_one_cm":8394,"minecraft:walk_one_cm":1806003,"minecraft:sneak_time":22939,"minecraft:walk_under_water_one_cm":27699,"minecraft:interact_with_lectern":2,"minecraft:total_world_time":706773,"minecraft:tune_noteblock":3,"minecraft:interact_with_stonecutter":25,"minecraft:time_since_rest":371865,"minecraft:damage_taken":1973,"minecraft:pokemon_registered":7,"minecraft:swim_one_cm":224,"minecraft:fly_one_cm":1057713,"minecraft:open_chest":84,"minecraft:fall_one_cm":34397},"minecraft:dropped":{"minecraft:lapis_lazuli":1,"minecraft:dark_oak_slab":6,"minecraft:lantern":1,"minecraft:cracked_stone_bricks":14,"minecraft:red_carpet":1,"minecraft:dirt":85,"minecraft:dark_oak_fence":1,"biomeswevegone:ebony_fence":1,"minecraft:oak_door":1,"minecraft:gravel":1,"minecraft:stone_axe":1,"minecraft:cobbled_deepslate":6,"minecraft:soul_lantern":1,"minecraft:deepslate_brick_slab":1,"minecraft:rotten_flesh":1,"minecraft:oak_planks":14,"stoneworks:stone_plates":1,"minecraft:glowstone":1,"minecraft:spruce_pressure_plate":1,"minecraft:azalea":3,"minecraft:egg":1,"minecraft:enchanted_book":5,"regions_unexplored:fireweed":8,"minecraft:wheat_seeds":8,"minecraft:mossy_cobblestone":1,"stoneworks:stone_tiles":3,"rechiseled:dark_oak_planks_tiles_connecting":1,"minecraft:barrier":1,"minecraft:cobblestone":58,"minecraft:coal":15,"regions_unexplored:daisy":5,"minecraft:stick":3,"minecraft:deepslate_brick_stairs":1,"minecraft:repeater":2,"minecraft:white_concrete":7,"minecraft:mud":1,"minecraft:tripwire_hook":3,"stoneworks:calcite_brick_stairs":1,"minecraft:dandelion":1,"minecraft:cobblestone_wall":1,"minecraft:raw_copper":15,"minecraft:tuff":1,"regions_unexplored:mauve_planks":3,"regions_unexplored:hyssop":12,"minecraft:debug_stick":1,"regions_unexplored:pink_lupine":1,"minecraft:light":1,"rechiseled:quartz_block_chiseled_pillar_connecting":1,"minecraft:spruce_trapdoor":1,"minecraft:andesite":243,"minecraft:wooden_pickaxe":1},"minecraft:broken":{"minecraft:stone_axe":1,"minecraft:iron_pickaxe":1}},"DataVersion":3955}